webber/__init__.py
webber/core/__init__.py
webber/credits/__init__.py
webber/edges/__init__.py
webber/queue/__init__.py
webber/viz/__init__.py
webber/viz/templates/vis_gui.html
webber/xcoms/__init__.py
webber-0.2.0.dist-info/LICENSE.txt
webber-0.2.0.dist-info/METADATA
webber-0.2.0.dist-info/WHEEL
webber-0.2.0.dist-info/top_level.txt
webber-0.2.0.dist-info/RECORD
